{"product_image1":"uploads\/file_192200127363414e76b8e25426614321.jpg","product_image2":"uploads\/file_2908080296337fab6a406f623588686.jpg","product_image3":"","product_name":"BEYAZ Su S\u0131zd\u0131rmaz Lavabo Kenar Band\u0131 (KUTUSUZ)(3.2m)","product_stok":"6","product_fee":28.32,"product_not_kdv_fee":"24","product_sale_fee":23.6,"product_not_kdv_sale_fee":"20","product_kdv":"18","prouct_status":"1","product_description":"Renk: Beyaz","product_specification":"<p>&nbsp;<\/p>\r\n<div class=\"tab-content  col-xs-12\">\r\n<div id=\"tab-description\" class=\"tab-pane active\">\r\n<h3 class=\"product-property-title\">&Uuml;r&uuml;n A&ccedil;\u0131klamas\u0131<\/h3>\r\n<div id=\"collapse-description\" class=\"desc-collapse showup\">\r\n<p>BEYAZ Su S\u0131zd\u0131rmaz Lavabo Kenar Band\u0131 (KUTUSUZ)(3.2m)<\/p>\r\n<p>S\u0131zd\u0131rmaz bant uzun&nbsp;&ouml;m&uuml;rl&uuml;&nbsp;bir&nbsp;s\u0131zd\u0131rmazl\u0131k&nbsp;sa\u011flar ve mutfak ve banyo alanlar\u0131na profesyonel bir g&ouml;r&uuml;n&uuml;m kazand\u0131r\u0131r.<\/p>\r\n<p><u><strong>Kullanmadan &ouml;nce band\u0131 yap\u0131\u015ft\u0131raca\u011f\u0131n\u0131z y&uuml;zeyin temiz ve kuru oldu\u011fundan emin olun.<\/strong><\/u><\/p>\r\n<table style=\"width: 50.0514%; height: 115px;\" border=\"1\" cellspacing=\"1\" cellpadding=\"1\">\r\n<tbody>\r\n<tr style=\"height: 44px;\">\r\n<td style=\"width: 31.6964%; height: 44px;\">\r\n<p>Renk<\/p>\r\n<\/td>\r\n<td style=\"width: 68.3036%; height: 44px;\">Beyaz,&nbsp;<\/td>\r\n<\/tr>\r\n<tr style=\"height: 16px;\">\r\n<td style=\"width: 31.6964%; height: 16px;\">A\u011f\u0131rl\u0131k<\/td>\r\n<td style=\"width: 68.3036%; height: 16px;\">Yakla\u015f\u0131k&nbsp;215g<\/td>\r\n<\/tr>\r\n<tr style=\"height: 55px;\">\r\n<td style=\"width: 31.6964%; height: 55px;\">Boyut<\/td>\r\n<td style=\"width: 68.3036%; height: 55px;\">3,2 m x&nbsp;38 mm<\/td>\r\n<\/tr>\r\n<\/tbody>\r\n<\/table>\r\n<\/div>\r\n<\/div>\r\n<\/div>","product_category_id":"28","product_barcode":"TE-406692","product_desi":"0.20","product_note":"","_id":64}